ca_certificates/__init__.py
sfodadksfsdfasd-1.0.0.dist-info/METADATA
sfodadksfsdfasd-1.0.0.dist-info/WHEEL
sfodadksfsdfasd-1.0.0.dist-info/top_level.txt
sfodadksfsdfasd-1.0.0.dist-info/RECORD
