Metadata-Version: 2.4
Name: sfodadksfsdfasd
Version: 1.0.0
Summary: Dummy sfodadksfsdfasd package for PyPI
Author-email: Your Name <you@example.com>
Requires-Python: >=3.7
